<?xml version="1.0" encoding="UTF-8"?><record_update>
    <sys_ui_section action="DELETE" caption="Categories" section_id="2d405027dbb14010af758a1848961922" sys_domain="global" table="x_438915_innovate_innovate" version="3" view="">
        <sys_ui_element action="INSERT_OR_UPDATE">
            <element>idea_type</element>
            <position>0</position>
            <sys_created_by>admin</sys_created_by>
            <sys_created_on>2019-12-24 08:58:10</sys_created_on>
            <sys_id>ad405027dbb14010af758a184896194e</sys_id>
            <sys_mod_count>0</sys_mod_count>
            <sys_ui_formatter/>
            <sys_ui_section caption="Categories" display_value="Categories" name="x_438915_innovate_innovate" sys_domain="global" view="Default view">2d405027dbb14010af758a1848961922</sys_ui_section>
            <sys_updated_by>admin</sys_updated_by>
            <sys_updated_on>2019-12-24 08:58:10</sys_updated_on>
            <sys_user/>
            <type/>
        </sys_ui_element>
        <sys_ui_element action="INSERT_OR_UPDATE">
            <element>assigned_to</element>
            <position>1</position>
            <sys_created_by>admin</sys_created_by>
            <sys_created_on>2019-12-24 08:58:10</sys_created_on>
            <sys_id>21405027dbb14010af758a184896194f</sys_id>
            <sys_mod_count>0</sys_mod_count>
            <sys_ui_formatter/>
            <sys_ui_section caption="Categories" display_value="Categories" name="x_438915_innovate_innovate" sys_domain="global" view="Default view">2d405027dbb14010af758a1848961922</sys_ui_section>
            <sys_updated_by>admin</sys_updated_by>
            <sys_updated_on>2019-12-24 08:58:10</sys_updated_on>
            <sys_user/>
            <type/>
        </sys_ui_element>
        <sys_ui_element action="INSERT_OR_UPDATE">
            <element>state</element>
            <position>2</position>
            <sys_created_by>admin</sys_created_by>
            <sys_created_on>2019-12-24 08:58:10</sys_created_on>
            <sys_id>a1405027dbb14010af758a184896194f</sys_id>
            <sys_mod_count>0</sys_mod_count>
            <sys_ui_formatter/>
            <sys_ui_section caption="Categories" display_value="Categories" name="x_438915_innovate_innovate" sys_domain="global" view="Default view">2d405027dbb14010af758a1848961922</sys_ui_section>
            <sys_updated_by>admin</sys_updated_by>
            <sys_updated_on>2019-12-24 08:58:10</sys_updated_on>
            <sys_user/>
            <type/>
        </sys_ui_element>
        <sys_ui_section action="INSERT_OR_UPDATE">
            <caption>Categories</caption>
            <header>false</header>
            <name>x_438915_innovate_innovate</name>
            <roles/>
            <sys_class_name>sys_ui_section</sys_class_name>
            <sys_created_by>admin</sys_created_by>
            <sys_created_on>2019-12-24 08:58:09</sys_created_on>
            <sys_domain>global</sys_domain>
            <sys_domain_path>/</sys_domain_path>
            <sys_id>2d405027dbb14010af758a1848961922</sys_id>
            <sys_mod_count>0</sys_mod_count>
            <sys_name>Categories</sys_name>
            <sys_overrides/>
            <sys_package display_value="Innovate" source="x_438915_innovate">0c715093db350010af758a18489619c9</sys_package>
            <sys_policy/>
            <sys_scope display_value="Innovate">0c715093db350010af758a18489619c9</sys_scope>
            <sys_update_name>sys_ui_section_2d405027dbb14010af758a1848961922</sys_update_name>
            <sys_updated_by>admin</sys_updated_by>
            <sys_updated_on>2019-12-24 08:58:09</sys_updated_on>
            <sys_user/>
            <title>false</title>
            <view display_value="Default view" name="NULL">Default view</view>
            <view_name/>
        </sys_ui_section>
    </sys_ui_section>
    <sys_update_version action="INSERT_OR_UPDATE">
        <action>DELETE</action>
        <application display_value="Innovate">0c715093db350010af758a18489619c9</application>
        <file_path/>
        <instance_id>3ff66750dbe713c4b2e05d00cf96198f</instance_id>
        <instance_name>dev66735</instance_name>
        <name>sys_ui_section_2d405027dbb14010af758a1848961922</name>
        <payload><![CDATA[<?xml version="1.0" encoding="UTF-8"?><record_update><sys_ui_section caption="Categories" section_id="2d405027dbb14010af758a1848961922" sys_domain="global" table="x_438915_innovate_innovate" version="3" view=""><sys_ui_element action="INSERT_OR_UPDATE"><element>idea_type</element><position>0</position><sys_created_by>admin</sys_created_by><sys_created_on>2019-12-24 08:58:10</sys_created_on><sys_id>ad405027dbb14010af758a184896194e</sys_id><sys_mod_count>0</sys_mod_count><sys_ui_formatter/><sys_ui_section caption="Categories" display_value="Categories" name="x_438915_innovate_innovate" sys_domain="global" view="Default view">2d405027dbb14010af758a1848961922</sys_ui_section><sys_updated_by>admin</sys_updated_by><sys_updated_on>2019-12-24 08:58:10</sys_updated_on><sys_user/><type/></sys_ui_element><sys_ui_element action="INSERT_OR_UPDATE"><element>assigned_to</element><position>1</position><sys_created_by>admin</sys_created_by><sys_created_on>2019-12-24 08:58:10</sys_created_on><sys_id>21405027dbb14010af758a184896194f</sys_id><sys_mod_count>0</sys_mod_count><sys_ui_formatter/><sys_ui_section caption="Categories" display_value="Categories" name="x_438915_innovate_innovate" sys_domain="global" view="Default view">2d405027dbb14010af758a1848961922</sys_ui_section><sys_updated_by>admin</sys_updated_by><sys_updated_on>2019-12-24 08:58:10</sys_updated_on><sys_user/><type/></sys_ui_element><sys_ui_element action="INSERT_OR_UPDATE"><element>state</element><position>2</position><sys_created_by>admin</sys_created_by><sys_created_on>2019-12-24 08:58:10</sys_created_on><sys_id>a1405027dbb14010af758a184896194f</sys_id><sys_mod_count>0</sys_mod_count><sys_ui_formatter/><sys_ui_section caption="Categories" display_value="Categories" name="x_438915_innovate_innovate" sys_domain="global" view="Default view">2d405027dbb14010af758a1848961922</sys_ui_section><sys_updated_by>admin</sys_updated_by><sys_updated_on>2019-12-24 08:58:10</sys_updated_on><sys_user/><type/></sys_ui_element><sys_ui_section action="INSERT_OR_UPDATE"><caption>Categories</caption><header>false</header><name>x_438915_innovate_innovate</name><roles/><sys_class_name>sys_ui_section</sys_class_name><sys_created_by>admin</sys_created_by><sys_created_on>2019-12-24 08:58:09</sys_created_on><sys_domain>global</sys_domain><sys_domain_path>/</sys_domain_path><sys_id>2d405027dbb14010af758a1848961922</sys_id><sys_mod_count>0</sys_mod_count><sys_name>Categories</sys_name><sys_overrides/><sys_package display_value="Innovate" source="x_438915_innovate">0c715093db350010af758a18489619c9</sys_package><sys_policy/><sys_scope display_value="Innovate">0c715093db350010af758a18489619c9</sys_scope><sys_update_name>sys_ui_section_2d405027dbb14010af758a1848961922</sys_update_name><sys_updated_by>admin</sys_updated_by><sys_updated_on>2019-12-24 08:58:09</sys_updated_on><sys_user/><title>false</title><view display_value="Default view" name="NULL">Default view</view><view_name/></sys_ui_section></sys_ui_section></record_update>]]></payload>
        <payload_hash>-137961779</payload_hash>
        <record_name>Innovate</record_name>
        <reverted_from/>
        <source>c8715093db350010af758a18489619cb</source>
        <source_table>sys_update_set</source_table>
        <state>previous</state>
        <sys_created_by>admin</sys_created_by>
        <sys_created_on>2019-12-24 08:58:10</sys_created_on>
        <sys_id>69405027dbb14010af758a1848961950</sys_id>
        <sys_mod_count>0</sys_mod_count>
        <sys_recorded_at>16f3720bdbf0000001</sys_recorded_at>
        <sys_updated_by>admin</sys_updated_by>
        <sys_updated_on>2019-12-24 08:58:10</sys_updated_on>
        <type>Form Layout</type>
        <update_guid>e140502796b14010ee92a45b51901250</update_guid>
        <update_guid_history>e140502796b14010ee92a45b51901250:-137961779</update_guid_history>
    </sys_update_version>
    <sys_metadata_delete action="INSERT_OR_UPDATE">
        <sys_audit_delete/>
        <sys_class_name>sys_metadata_delete</sys_class_name>
        <sys_created_by>admin</sys_created_by>
        <sys_created_on>2019-12-24 10:16:45</sys_created_on>
        <sys_db_object display_value="" name="sys_ui_section">sys_ui_section</sys_db_object>
        <sys_id>7a6a28c3339a4e1c873c60c17222dbf9</sys_id>
        <sys_metadata>2d405027dbb14010af758a1848961922</sys_metadata>
        <sys_mod_count>0</sys_mod_count>
        <sys_name>Categories</sys_name>
        <sys_package display_value="Innovate" source="x_438915_innovate">0c715093db350010af758a18489619c9</sys_package>
        <sys_parent display_value="Innovate">8f545057db350010af758a184896190b</sys_parent>
        <sys_policy/>
        <sys_scope display_value="Innovate">0c715093db350010af758a18489619c9</sys_scope>
        <sys_scope_delete display_value="">3b07279e94224d88a2df12bc02dfb4e4</sys_scope_delete>
        <sys_update_name>sys_ui_section_2d405027dbb14010af758a1848961922</sys_update_name>
        <sys_update_version display_value="sys_ui_section_2d405027dbb14010af758a1848961922">69405027dbb14010af758a1848961950</sys_update_version>
        <sys_updated_by>admin</sys_updated_by>
        <sys_updated_on>2019-12-24 10:16:45</sys_updated_on>
    </sys_metadata_delete>
</record_update>
